tigergraph_mlworkbench/__init__.py
tigergraph_mlworkbench/_version.py
tigergraph_mlworkbench/labextension/package.json
tigergraph_mlworkbench/labextension/schemas/@tigergraph/mlworkbench/extension.json
tigergraph_mlworkbench/labextension/schemas/@tigergraph/mlworkbench/package.json.orig
tigergraph_mlworkbench/labextension/static/573.13c3b6d3c5aa061a70a3.js
tigergraph_mlworkbench/labextension/static/747.dc8f0513da913535dd28.js
tigergraph_mlworkbench/labextension/static/remoteEntry.531719faf302b74f0624.js
tigergraph_mlworkbench/labextension/static/style.js
tigergraph_mlworkbench/labextension/static/third-party-licenses.json
tigergraph_mlworkbench-1.0.0.data/data/share/jupyter/labextensions/@tigergraph/mlworkbench/install.json
tigergraph_mlworkbench-1.0.0.data/data/share/jupyter/labextensions/@tigergraph/mlworkbench/package.json
tigergraph_mlworkbench-1.0.0.data/data/share/jupyter/labextensions/@tigergraph/mlworkbench/schemas/@tigergraph/mlworkbench/extension.json
tigergraph_mlworkbench-1.0.0.data/data/share/jupyter/labextensions/@tigergraph/mlworkbench/schemas/@tigergraph/mlworkbench/package.json.orig
tigergraph_mlworkbench-1.0.0.data/data/share/jupyter/labextensions/@tigergraph/mlworkbench/static/573.13c3b6d3c5aa061a70a3.js
tigergraph_mlworkbench-1.0.0.data/data/share/jupyter/labextensions/@tigergraph/mlworkbench/static/747.dc8f0513da913535dd28.js
tigergraph_mlworkbench-1.0.0.data/data/share/jupyter/labextensions/@tigergraph/mlworkbench/static/remoteEntry.531719faf302b74f0624.js
tigergraph_mlworkbench-1.0.0.data/data/share/jupyter/labextensions/@tigergraph/mlworkbench/static/style.js
tigergraph_mlworkbench-1.0.0.data/data/share/jupyter/labextensions/@tigergraph/mlworkbench/static/third-party-licenses.json
tigergraph_mlworkbench-1.0.0.dist-info/LICENSE
tigergraph_mlworkbench-1.0.0.dist-info/METADATA
tigergraph_mlworkbench-1.0.0.dist-info/WHEEL
tigergraph_mlworkbench-1.0.0.dist-info/top_level.txt
tigergraph_mlworkbench-1.0.0.dist-info/RECORD
